ItchClaim/CfWrapper.py
ItchClaim/DiskManager.py
ItchClaim/ItchGame.py
ItchClaim/ItchSale.py
ItchClaim/ItchUser.py
ItchClaim/__init__.py
ItchClaim/__main__.py
ItchClaim/index.template.html
ItchClaim/web.py
ItchClaim/flaresolverr/CHANGELOG.md
ItchClaim/flaresolverr/Dockerfile
ItchClaim/flaresolverr/LICENSE
ItchClaim/flaresolverr/README.md
ItchClaim/flaresolverr/docker-compose.yml
ItchClaim/flaresolverr/flaresolverr.py
ItchClaim/flaresolverr/flaresolverr.service
ItchClaim/flaresolverr/package.json
ItchClaim/flaresolverr/pyproject.toml
ItchClaim/flaresolverr/requirements.txt
ItchClaim/flaresolverr/test-requirements.txt
ItchClaim/flaresolverr/flaresolverr/__init__.py
ItchClaim/flaresolverr/flaresolverr/build_package.py
ItchClaim/flaresolverr/flaresolverr/dtos.py
ItchClaim/flaresolverr/flaresolverr/flaresolverr.py
ItchClaim/flaresolverr/flaresolverr/flaresolverr_service.py
ItchClaim/flaresolverr/flaresolverr/metrics.py
ItchClaim/flaresolverr/flaresolverr/sessions.py
ItchClaim/flaresolverr/flaresolverr/tests.py
ItchClaim/flaresolverr/flaresolverr/tests_sites.py
ItchClaim/flaresolverr/flaresolverr/utils.py
ItchClaim/flaresolverr/flaresolverr/bottle_plugins/__init__.py
ItchClaim/flaresolverr/flaresolverr/bottle_plugins/error_plugin.py
ItchClaim/flaresolverr/flaresolverr/bottle_plugins/logger_plugin.py
ItchClaim/flaresolverr/flaresolverr/bottle_plugins/prometheus_plugin.py
ItchClaim/flaresolverr/flaresolverr/undetected_chromedriver/__init__.py
ItchClaim/flaresolverr/flaresolverr/undetected_chromedriver/cdp.py
ItchClaim/flaresolverr/flaresolverr/undetected_chromedriver/devtool.py
ItchClaim/flaresolverr/flaresolverr/undetected_chromedriver/dprocess.py
ItchClaim/flaresolverr/flaresolverr/undetected_chromedriver/options.py
ItchClaim/flaresolverr/flaresolverr/undetected_chromedriver/patcher.py
ItchClaim/flaresolverr/flaresolverr/undetected_chromedriver/reactor.py
ItchClaim/flaresolverr/flaresolverr/undetected_chromedriver/webelement.py
itchclaim-1.9.2.dist-info/METADATA
itchclaim-1.9.2.dist-info/WHEEL
itchclaim-1.9.2.dist-info/entry_points.txt
itchclaim-1.9.2.dist-info/top_level.txt
itchclaim-1.9.2.dist-info/RECORD
