Metadata-Version: 2.4
Name: ItchClaim
Version: 1.9.2
Summary: Automatically claim free games from itch.io
Author: Smart123s
Project-URL: Homepage, https://github.com/Smart123s/ItchClaim
Project-URL: Bug Tracker, https://github.com/Smart123s/ItchClaim/issues
Classifier: Development Status :: 5 - Production/Stable
Classifier: Environment :: Console
Classifier: Intended Audience :: End Users/Desktop
Classifier: Intended Audience :: Developers
Classifier: License :: OSI Approved :: MIT License
Classifier: Operating System :: OS Independent
Classifier: Programming Language :: Python :: 3.8
Classifier: Programming Language :: Python :: 3.9
Classifier: Programming Language :: Python :: 3.10
Classifier: Programming Language :: Python :: 3.11
Classifier: Programming Language :: Python :: 3.12
Classifier: Programming Language :: Python :: 3 :: Only
Classifier: Topic :: Internet
Requires-Python: >=3.8
Requires-Dist: requests>=2.32.5
Requires-Dist: fire>=0.6.0
Requires-Dist: pyotp>=2.9.0
Requires-Dist: beautifulsoup4>=4.12.3
Requires-Dist: pycron>=3.0.0
Requires-Dist: bottle==0.13.4
Requires-Dist: waitress==3.0.2
Requires-Dist: selenium==4.38.0
Requires-Dist: func-timeout==4.3.5
Requires-Dist: prometheus-client==0.23.1
Requires-Dist: requests==2.32.5
Requires-Dist: certifi==2025.10.5
Requires-Dist: websockets==15.0.1
Requires-Dist: packaging==25.0
Requires-Dist: xvfbwrapper==0.2.15; platform_system != "Windows"
Requires-Dist: pefile==2024.8.26; platform_system == "Windows"
